lib_ddos_simulator/__init__.py
lib_ddos_simulator/__main__.py
lib_ddos_simulator/base_grapher.py
lib_ddos_simulator/utils.py
lib_ddos_simulator/animations/__init__.py
lib_ddos_simulator/animations/anim_attacker.py
lib_ddos_simulator/animations/anim_bucket.py
lib_ddos_simulator/animations/anim_round_text.py
lib_ddos_simulator/animations/anim_user.py
lib_ddos_simulator/animations/animater.py
lib_ddos_simulator/animations/bucket_states.py
lib_ddos_simulator/animations/color_generator.py
lib_ddos_simulator/attackers/__init__.py
lib_ddos_simulator/attackers/attacker.py
lib_ddos_simulator/attackers/basic_attacker.py
lib_ddos_simulator/attackers/even_turn_attacker.py
lib_ddos_simulator/attackers/never_alone_attacker.py
lib_ddos_simulator/attackers/never_last_attacker.py
lib_ddos_simulator/attackers/patient_attacker.py
lib_ddos_simulator/attackers/random_attacker.py
lib_ddos_simulator/attackers/x_turns_straight_attacker.py
lib_ddos_simulator/ddos_simulators/__init__.py
lib_ddos_simulator/ddos_simulators/ddos_simulator.py
lib_ddos_simulator/graphers/__init__.py
lib_ddos_simulator/graphers/combination_grapher.py
lib_ddos_simulator/graphers/combo_data_generator.py
lib_ddos_simulator/graphers/grapher.py
lib_ddos_simulator/graphers/tests/__init__.py
lib_ddos_simulator/graphers/tests/test_animator.py
lib_ddos_simulator/graphers/tests/test_grapher.py
lib_ddos_simulator/managers/__init__.py
lib_ddos_simulator/managers/bounded_manager.py
lib_ddos_simulator/managers/manager.py
lib_ddos_simulator/managers/motag.py
lib_ddos_simulator/managers/dose/__init__.py
lib_ddos_simulator/managers/dose/dose_attack_event.py
lib_ddos_simulator/managers/dose/dose_manager.py
lib_ddos_simulator/managers/protag/__init__.py
lib_ddos_simulator/managers/protag/protag_manager_base.py
lib_ddos_simulator/managers/protag/protag_manager_merge.py
lib_ddos_simulator/managers/protag/protag_manager_no_merge.py
lib_ddos_simulator/managers/protag/protag_manager_smart_merge.py
lib_ddos_simulator-0.1.2.dist-info/AUTHORS
lib_ddos_simulator-0.1.2.dist-info/LICENSE
lib_ddos_simulator-0.1.2.dist-info/METADATA
lib_ddos_simulator-0.1.2.dist-info/WHEEL
lib_ddos_simulator-0.1.2.dist-info/entry_points.txt
lib_ddos_simulator-0.1.2.dist-info/top_level.txt
lib_ddos_simulator-0.1.2.dist-info/RECORD
