Metadata-Version: 2.1
Name: lib-ddos-simulator
Version: 0.1.2
Summary: DDOS simulator
Home-page: https://github.com/jfuruness/lib_ddos_simulator.git
Author: Justin Furuness and Anna Gorbenko
Author-email: jfuruness@gmail.com, agorbenko97@gmail.com
License: UNKNOWN
Download-URL: https://github.com/jfuruness/lib_ddos.git
Keywords: Furuness,Gorbenko,DDOS,DOS,Simulation,Sieve,Protag,KPO,DOSE,Distributed Denial of Service,Denial of Service
Platform: UNKNOWN
Classifier: Environment :: Console
Classifier: Intended Audience :: Developers
Classifier: License :: OSI Approved :: BSD License
Classifier: Programming Language :: Python :: 3
Requires-Dist: flasgger
Requires-Dist: flask
Requires-Dist: matplotlib
Requires-Dist: pathos
Requires-Dist: pytest
Requires-Dist: scipy
Requires-Dist: setuptools
Requires-Dist: tikzplotlib
Requires-Dist: tqdm
Requires-Dist: wheel
